text_to_qti/__init__.py
text_to_qti/__main__.py
text_to_qti/cli.py
text_to_qti/py.typed
text_to_qti/packager/__init__.py
text_to_qti/packager/zip_creator.py
text_to_qti/parser/__init__.py
text_to_qti/parser/markdown_parser.py
text_to_qti/parser/question_models.py
text_to_qti/parser/syntax_validator.py
text_to_qti/qti/__init__.py
text_to_qti/qti/assessment.py
text_to_qti/qti/base_item.py
text_to_qti/qti/canvas_metadata.py
text_to_qti/qti/generator.py
text_to_qti/qti/manifest.py
text_to_qti/qti/utils.py
text_to_qti/qti/items/__init__.py
text_to_qti/qti/items/multiple_choice.py
text_to_qti/qti/items/true_false.py
text_to_qti/utils/__init__.py
text_to_qti/utils/errors.py
text_to_qti-0.1.1.dist-info/licenses/AUTHORS
text_to_qti-0.1.1.dist-info/licenses/LICENSE
text_to_qti-0.1.1.dist-info/METADATA
text_to_qti-0.1.1.dist-info/WHEEL
text_to_qti-0.1.1.dist-info/entry_points.txt
text_to_qti-0.1.1.dist-info/top_level.txt
text_to_qti-0.1.1.dist-info/RECORD
