Metadata-Version: 2.4
Name: text-to-qti
Version: 0.1.1
Summary: Convert markdown-based quiz text files to QTI format for Canvas LMS, built with Claude AI assistance
Author-email: Eric Magto <tableaprogramming@gmail.com>
License: MIT
Project-URL: Homepage, https://github.com/tableaprogramming-rgb/textmd-to-qti
Project-URL: Repository, https://github.com/tableaprogramming-rgb/textmd-to-qti
Project-URL: Documentation, https://github.com/tableaprogramming-rgb/textmd-to-qti#readme
Project-URL: Bug Tracker, https://github.com/tableaprogramming-rgb/textmd-to-qti/issues
Keywords: qti,canvas,quiz,conversion,markdown
Classifier: Development Status :: 3 - Alpha
Classifier: Intended Audience :: Education
Classifier: Intended Audience :: Developers
Classifier: Topic :: Education :: Testing
Classifier: License :: OSI Approved :: MIT License
Classifier: Operating System :: OS Independent
Classifier: Programming Language :: Python :: 3
Classifier: Programming Language :: Python :: 3.8
Classifier: Programming Language :: Python :: 3.9
Classifier: Programming Language :: Python :: 3.10
Classifier: Programming Language :: Python :: 3.11
Classifier: Programming Language :: Python :: 3.12
Classifier: Programming Language :: Python :: 3.13
Classifier: Typing :: Typed
Classifier: Framework :: Pydantic
Requires-Python: >=3.8
License-File: LICENSE
License-File: AUTHORS
Requires-Dist: lxml<7.0.0,>=5.3.0
Requires-Dist: pydantic<3.0.0,>=2.10.0
Requires-Dist: click<9.0.0,>=8.1.0
Requires-Dist: rich<15.0.0,>=13.0.0
Requires-Dist: markdown<4.0.0,>=3.5.0
Requires-Dist: PyYAML<7.0.0,>=6.0.0
Provides-Extra: dev
Requires-Dist: pytest>=7.4.0; extra == "dev"
Requires-Dist: pytest-cov>=4.1.0; extra == "dev"
Requires-Dist: black>=23.0.0; extra == "dev"
Requires-Dist: ruff>=0.1.0; extra == "dev"
Requires-Dist: mypy>=1.5.0; extra == "dev"
Dynamic: license-file
